tensorflow_data_validation/__init__.py
tensorflow_data_validation/constants.py
tensorflow_data_validation/types.py
tensorflow_data_validation/types_test.py
tensorflow_data_validation/version.py
tensorflow_data_validation/anomalies/__init__.py
tensorflow_data_validation/anomalies/proto/__init__.py
tensorflow_data_validation/anomalies/proto/custom_validation_config_pb2.py
tensorflow_data_validation/anomalies/proto/validation_config_pb2.py
tensorflow_data_validation/anomalies/proto/validation_metadata_pb2.py
tensorflow_data_validation/api/__init__.py
tensorflow_data_validation/api/stats_api.py
tensorflow_data_validation/api/stats_api_test.py
tensorflow_data_validation/api/validation_api.py
tensorflow_data_validation/api/validation_api_test.py
tensorflow_data_validation/api/validation_options.py
tensorflow_data_validation/api/validation_options_test.py
tensorflow_data_validation/arrow/__init__.py
tensorflow_data_validation/arrow/arrow_util.py
tensorflow_data_validation/arrow/arrow_util_test.py
tensorflow_data_validation/arrow/decoded_examples_to_arrow.py
tensorflow_data_validation/arrow/decoded_examples_to_arrow_test.py
tensorflow_data_validation/coders/__init__.py
tensorflow_data_validation/coders/csv_decoder.py
tensorflow_data_validation/coders/csv_decoder_test.py
tensorflow_data_validation/pywrap/__init__.py
tensorflow_data_validation/pywrap/tensorflow_data_validation_extension.so
tensorflow_data_validation/skew/__init__.py
tensorflow_data_validation/skew/feature_skew_detector.py
tensorflow_data_validation/skew/feature_skew_detector_test.py
tensorflow_data_validation/skew/protos/__init__.py
tensorflow_data_validation/skew/protos/feature_skew_results_pb2.py
tensorflow_data_validation/statistics/__init__.py
tensorflow_data_validation/statistics/stats_impl.py
tensorflow_data_validation/statistics/stats_impl_test.py
tensorflow_data_validation/statistics/stats_options.py
tensorflow_data_validation/statistics/stats_options_test.py
tensorflow_data_validation-1.17.0.dist-info/METADATA
tensorflow_data_validation-1.17.0.dist-info/WHEEL
tensorflow_data_validation-1.17.0.dist-info/namespace_packages.txt
tensorflow_data_validation-1.17.0.dist-info/top_level.txt
tensorflow_data_validation-1.17.0.dist-info/RECORD
tensorflow_data_validation-1.17.0.dist-info/licenses/LICENSE
