Metadata-Version: 2.4
Name: tensorflow-data-validation
Version: 1.17.0
Summary: A library for exploring and validating machine learning data.
Home-page: https://www.tensorflow.org/tfx/data_validation/get_started
Download-URL: https://github.com/tensorflow/data-validation/tags
Author: Google LLC
Author-email: tensorflow-extended-dev@googlegroups.com
License: Apache 2.0
Keywords: tensorflow data validation tfx
Classifier: Development Status :: 5 - Production/Stable
Classifier: Intended Audience :: Developers
Classifier: Intended Audience :: Education
Classifier: Intended Audience :: Science/Research
Classifier: License :: OSI Approved :: Apache Software License
Classifier: Operating System :: MacOS :: MacOS X
Classifier: Operating System :: POSIX :: Linux
Classifier: Programming Language :: Python
Classifier: Programming Language :: Python :: 3
Classifier: Programming Language :: Python :: 3.9
Classifier: Programming Language :: Python :: 3.10
Classifier: Programming Language :: Python :: 3.11
Classifier: Programming Language :: Python :: 3 :: Only
Classifier: Topic :: Scientific/Engineering
Classifier: Topic :: Scientific/Engineering :: Artificial Intelligence
Classifier: Topic :: Scientific/Engineering :: Mathematics
Classifier: Topic :: Software Development
Classifier: Topic :: Software Development :: Libraries
Classifier: Topic :: Software Development :: Libraries :: Python Modules
Requires-Python: >=3.9,<4
License-File: LICENSE
Requires-Dist: absl-py<2.0.0,>=0.9
Requires-Dist: apache-beam[gcp]<3,>=2.53; python_version >= "3.11"
Requires-Dist: apache-beam[gcp]<2.51,>=2.50; python_version < "3.11"
Requires-Dist: joblib>=1.2.0
Requires-Dist: numpy>=1.22.0
Requires-Dist: pandas<2,>=1.0
Requires-Dist: protobuf<6.0.0,>=4.25.2; python_version >= "3.11"
Requires-Dist: protobuf<6.0.0,>=4.21.6; python_version < "3.11"
Requires-Dist: pyarrow<11,>=10
Requires-Dist: pyfarmhash<0.4,>=0.2.2
Requires-Dist: six<2,>=1.12
Requires-Dist: tensorflow<2.18,>=2.17
Requires-Dist: tensorflow-metadata<1.18,>=1.17.1
Requires-Dist: tfx-bsl<1.18,>=1.17.1
Provides-Extra: mutual-information
Requires-Dist: scikit-learn<2,>=1.0; extra == "mutual-information"
Requires-Dist: scipy<2,>=1.5; extra == "mutual-information"
Provides-Extra: visualization
Requires-Dist: ipython<8,>=7; extra == "visualization"
Provides-Extra: all
Requires-Dist: scikit-learn<2,>=1.0; extra == "all"
Requires-Dist: scipy<2,>=1.5; extra == "all"
Requires-Dist: ipython<8,>=7; extra == "all"
Dynamic: author
Dynamic: author-email
Dynamic: classifier
Dynamic: description
Dynamic: description-content-type
Dynamic: download-url
Dynamic: home-page
Dynamic: keywords
Dynamic: license
Dynamic: license-file
Dynamic: provides-extra
Dynamic: requires-dist
Dynamic: requires-python
Dynamic: summary
